analysis/__init__.py
analysis/utils.py
experiment/__init__.py
experiment/utils.py
model/__init__.py
model/utils.py
neuro/__init__.py
neuro/utils.py
fastbrain-0.0.0.dist-info/LICENSE
fastbrain-0.0.0.dist-info/METADATA
fastbrain-0.0.0.dist-info/WHEEL
fastbrain-0.0.0.dist-info/top_level.txt
fastbrain-0.0.0.dist-info/RECORD
