Metadata-Version: 2.1
Name: fastbrain
Version: 0.0.0
Summary: Python library of of jax-based representational studies in neuroscience and deep learning
Home-page: https://github.com/doerlbh/fastbrain
Author: Baihan Lin
Author-email: doerlbh@gmail.com
License: MIT
Project-URL: Bug Tracker, https://github.com/doerlbh/fastbrain/issues
Platform: UNKNOWN
Classifier: Programming Language :: Python :: 3
Classifier: License :: OSI Approved :: MIT License
Classifier: Operating System :: OS Independent
Requires-Python: >=3.6
Requires-Dist: jax
Requires-Dist: numpy (>=1.16.5)
Requires-Dist: pandas
